torchspd/__init__.py
torchspd/torchspd.py
torchspd-0.1.2.dist-info/licenses/LICENSE
torchspd-0.1.2.dist-info/METADATA
torchspd-0.1.2.dist-info/WHEEL
torchspd-0.1.2.dist-info/top_level.txt
torchspd-0.1.2.dist-info/RECORD
