Metadata-Version: 2.4
Name: torchspd
Version: 0.1.2
Summary: Differentiable spectral operators on symmetric positive definite (SPD) matrices in PyTorch
Author: Samuel Boïté
License: MIT License
Project-URL: Homepage, https://github.com/samuelbx/torchspd
Project-URL: Documentation, https://github.com/samuelbx/torchspd#readme
Project-URL: Source, https://github.com/samuelbx/torchspd
Project-URL: Tracker, https://github.com/samuelbx/torchspd/issues
Keywords: pytorch,symmetric positive definite,matrix functions,linear algebra,autograd,logm,sqrtm,expm,numerical linear algebra
Classifier: Development Status :: 3 - Alpha
Classifier: Intended Audience :: Science/Research
Classifier: License :: OSI Approved :: MIT License
Classifier: Programming Language :: Python
Classifier: Programming Language :: Python :: 3
Classifier: Programming Language :: Python :: 3 :: Only
Classifier: Programming Language :: Python :: 3.9
Classifier: Programming Language :: Python :: 3.10
Classifier: Programming Language :: Python :: 3.11
Classifier: Programming Language :: Python :: 3.12
Classifier: Topic :: Scientific/Engineering :: Artificial Intelligence
Classifier: Topic :: Scientific/Engineering :: Mathematics
Classifier: Operating System :: OS Independent
Requires-Python: >=3.9
License-File: LICENSE
Requires-Dist: torch>=2.1
Dynamic: license-file
